Metadata-Version: 1.1
Name: msg
Version: 0.7.8
Summary: msg server backend
Home-page: UNKNOWN
Author: Lily Seabreeze
Author-email: lillian.gardenia.seabreeze@gmail.com
License: MIT
Platform: UNKNOWN
Classifier: Development Status :: 3 - Alpha
Classifier: Intended Audience :: Developers
Classifier: Natural Language :: English
Classifier: Programming Language :: Python :: 2.7
Classifier: Programming Language :: Python :: 3.5
